{
	"position_0": {
		"pos": [1434, 26049],
		"label": "PlayerBase"
	},
	"position_1": {
		"pos": [5809, 26152],
		"label": "PlayerHill"
	},
	"position_2": {
		"pos": [11795, 31701],
		"label": "Defend1_0"
	},
	"position_3": {
		"pos": [10755, 23942],
		"label": "Assembly2"
	},
	"position_4": {
		"pos": [13611, 31751],
		"label": "Assembly1"
	},
	"position_5": {
		"pos": [1595, 20561],
		"label": "Assembly0"
	},
	"position_6": {
		"pos": [2760, 19876],
		"label": "Patrol0_1"
	},
	"position_7": {
		"pos": [4060, 19358],
		"label": "Patrol0_2"
	},
	"position_8": {
		"pos": [3639, 23448],
		"label": "Patrol0_3"
	},
	"position_9": {
		"pos": [2218, 23078],
		"label": "Patrol0_4"
	},
	"position_10": {
		"pos": [1368, 22359],
		"label": "Patrol0_5"
	},
	"position_11": {
		"pos": [8894, 24780],
		"label": "Patrol2_0"
	},
	"position_12": {
		"pos": [7822, 23361],
		"label": "Patrol2_1"
	},
	"position_13": {
		"pos": [11702, 31281],
		"label": "Patrol1_0"
	},
	"position_14": {
		"pos": [8624, 31338],
		"label": "Patrol1_1"
	},
	"position_15": {
		"pos": [10130, 20769],
		"label": "DefendZ"
	},
	"area_2": {
		"pos1": [8448, 17408],
		"pos2": [8960, 17920],
		"label": "restran"
	},
	"area_3": {
		"pos1": [640, 19968],
		"pos2": [2432, 21632],
		"label": "ScavBase0"
	},
	"area_4": {
		"pos1": [13312, 29952],
		"pos2": [16128, 32512],
		"label": "ScavBase1"
	},
	"area_5": {
		"pos1": [10368, 22784],
		"pos2": [11264, 23680],
		"label": "ScavBase2"
	},
	"area_6": {
		"pos1": [8064, 22272],
		"pos2": [9344, 23552],
		"label": "ScavPost0"
	},
	"area_7": {
		"pos1": [10240, 16896],
		"pos2": [10368, 19456],
		"label": "CAPTURE"
	},
	"area_8": {
		"pos1": [8576, 16896],
		"pos2": [8960, 17280],
		"label": "dertran1"
	},
	"area_9": {
		"pos1": [14336, 17920],
		"pos2": [14720, 18304],
		"label": "dertran3"
	},
	"area_10": {
		"pos1": [13568, 21504],
		"pos2": [13952, 21888],
		"label": "dertran2"
	},
	"area_11": {
		"pos1": [9216, 17792],
		"pos2": [9856, 18432],
		"label": "LandingZone"
	},
	"area_12": {
		"pos1": [9088, 19456],
		"pos2": [11264, 21760],
		"label": "NASDA"
	},
	"area_13": {
		"pos1": [9088, 19456],
		"pos2": [11264, 21760],
		"label": "NASDAZ"
	},
	"area_14": {
		"pos1": [8960, 21120],
		"pos2": [10624, 21888],
		"label": "NASDAO"
	},
	"object_3": {
		"id": 373,
		"type": 1,
		"player": 4,
		"label": "pgenarti"
	},
	"object_43": {
		"id": 43,
		"type": 1,
		"player": 7,
		"label": "ScavFac0"
	},
	"object_44": {
		"id": 380,
		"type": 1,
		"player": 4,
		"label": "cyfacarti"
	},
	"object_130": {
		"id": 147,
		"type": 1,
		"player": 7,
		"label": "ScavFac3"
	},
	"object_146": {
		"id": 146,
		"type": 1,
		"player": 7,
		"label": "ScavFac2"
	},
	"object_148": {
		"id": 44,
		"type": 1,
		"player": 7,
		"label": "ScavFac1"
	},
	"object_296": {
		"id": 148,
		"type": 1,
		"player": 7,
		"label": "ScavFac4"
	},
	"object_320": {
		"id": 344,
		"type": 1,
		"player": 4,
		"label": "wallarti"
	},
	"object_335": {
		"id": 365,
		"type": 1,
		"player": 4,
		"label": "reparti"
	},
	"object_340": {
		"id": 370,
		"type": 1,
		"player": 4,
		"label": "preqres2"
	},
	"object_341": {
		"id": 367,
		"type": 1,
		"player": 4,
		"label": "resarti"
	},
	"object_342": {
		"id": 303,
		"type": 1,
		"player": 7,
		"label": "ScavFac5"
	},
	"object_349": {
		"id": 368,
		"type": 1,
		"player": 4,
		"label": "preqres1"
	},
	"object_350": {
		"id": 369,
		"type": 1,
		"player": 4,
		"label": "preqres3"
	},
	"object_355": {
		"id": 361,
		"type": 1,
		"player": 4,
		"label": "facarti"
	},
	"object_356": {
		"id": 355,
		"type": 1,
		"player": 4,
		"label": "gatearti"
	},
	"object_361": {
		"id": 375,
		"type": 1,
		"player": 4,
		"label": "traparti"
	},
	"object_362": {
		"id": 360,
		"type": 1,
		"player": 4,
		"label": "crarti"
	},
	"object_367": {
		"id": 356,
		"type": 1,
		"player": 4,
		"label": "ccarti"
	}
}
